{"name":"aurelia-config","children":[{"id":2,"name":"BaseConfig","kind":128,"kindString":"Class","flags":{"isExported":true},"comment":{"shortText":"BaseConfig class"},"children":[{"id":6,"name":"constructor","kind":512,"kindString":"Constructor","flags":{"isExported":true},"comment":{"shortText":"Creates an instance of BaseConfig. Copies defaults into current"},"signatures":[{"id":7,"name":"new BaseConfig","kind":16384,"kindString":"Constructor signature","flags":{},"comment":{"shortText":"Creates an instance of BaseConfig. Copies defaults into current"},"parameters":[{"id":8,"name":"defaults","kind":32768,"kindString":"Parameter","flags":{"isOptional":true},"comment":{"shortText":"Set the defaults. Required!\n"},"type":{"type":"instrinct","name":"any"}}],"type":{"type":"reference","name":"BaseConfig","id":2}}]},{"id":5,"name":"alias","kind":1024,"kindString":"Property","flags":{"isExported":true},"comment":{"shortText":"Derived classes should set an alternative alias","tags":[{"tag":"param","text":"\n"}]},"type":{"type":"instrinct","name":"any"}},{"id":4,"name":"current","kind":1024,"kindString":"Property","flags":{"isExported":true},"comment":{"shortText":"The current values of your config","tags":[{"tag":"param","text":"\n"}]},"type":{"type":"instrinct","name":"any"}},{"id":3,"name":"defaults","kind":1024,"kindString":"Property","flags":{"isExported":true},"comment":{"shortText":"The defaults of your config","tags":[{"tag":"param","text":"\n"}]},"type":{"type":"instrinct","name":"any"}},{"id":12,"name":"delete","kind":2048,"kindString":"Method","flags":{"isExported":true},"signatures":[{"id":13,"name":"delete","kind":4096,"kindString":"Call signature","flags":{},"comment":{"shortText":"Deletes a value from the current configuration"},"parameters":[{"id":14,"name":"keys","kind":32768,"kindString":"Parameter","flags":{"isRest":true},"comment":{"text":"(dot-separated) string(s) or array of keys\n"},"type":{"type":"instrinct","isArray":true,"name":"any"}}],"type":{"type":"instrinct","name":"any"}}]},{"id":19,"name":"extend","kind":2048,"kindString":"Method","flags":{"isExported":true},"signatures":[{"id":20,"name":"extend","kind":4096,"kindString":"Call signature","flags":{},"comment":{"shortText":"Entends an oject value in the current configuration"},"parameters":[{"id":21,"name":"keys","kind":32768,"kindString":"Parameter","flags":{"isOptional":true},"comment":{"text":"(dot-separated) string(s) or array of keys"},"type":{"type":"instrinct","name":"any"}},{"id":22,"name":"value","kind":32768,"kindString":"Parameter","flags":{"isOptional":true},"comment":{"text":"The value to set\n"},"type":{"type":"instrinct","name":"any"}}],"type":{"type":"instrinct","name":"any"}}]},{"id":9,"name":"fetch","kind":2048,"kindString":"Method","flags":{"isExported":true},"signatures":[{"id":10,"name":"fetch","kind":4096,"kindString":"Call signature","flags":{},"comment":{"shortText":"Fetches a value from the current configuration","returns":"that The retrived value\n"},"parameters":[{"id":11,"name":"keys","kind":32768,"kindString":"Parameter","flags":{"isRest":true},"comment":{"text":"(dot-separated) string(s) or array of keys"},"type":{"type":"instrinct","isArray":true,"name":"any"}}],"type":{"type":"instrinct","name":"any"}}]},{"id":23,"name":"reset","kind":2048,"kindString":"Method","flags":{"isExported":true},"signatures":[{"id":24,"name":"reset","kind":4096,"kindString":"Call signature","flags":{},"comment":{"shortText":"Reset the current configuration back to defaults"},"parameters":[{"id":25,"name":"keys","kind":32768,"kindString":"Parameter","flags":{"isOptional":true},"comment":{"text":"(dot-separated) string(s) or array of keys"},"type":{"type":"instrinct","name":"any"}}],"type":{"type":"instrinct","name":"any"}}]},{"id":15,"name":"set","kind":2048,"kindString":"Method","flags":{"isExported":true},"signatures":[{"id":16,"name":"set","kind":4096,"kindString":"Call signature","flags":{},"comment":{"shortText":"Sets a value in the current configuration"},"parameters":[{"id":17,"name":"keys","kind":32768,"kindString":"Parameter","flags":{"isOptional":true},"comment":{"text":"(dot-separated) string(s) or array of keys"},"type":{"type":"instrinct","name":"any"}},{"id":18,"name":"value","kind":32768,"kindString":"Parameter","flags":{"isOptional":true},"comment":{"text":"The value to set\n"},"type":{"type":"instrinct","name":"any"}}],"type":{"type":"instrinct","name":"any"}}]}],"groups":[{"title":"Constructors","kind":512,"children":[6]},{"title":"Properties","kind":1024,"children":[5,4,3]},{"title":"Methods","kind":2048,"children":[12,19,9,23,15]}],"extendedBy":[{"type":"reference","name":"GlobalConfig","id":26}]},{"id":50,"name":"ConfigManager","kind":128,"kindString":"Class","flags":{"isExported":true},"comment":{"shortText":"The ConfigManager class\nRegister and retrieve configs"},"children":[{"id":54,"name":"constructor","kind":512,"kindString":"Constructor","flags":{"isExported":true},"comment":{"shortText":"Creates an instance of the ConfigManager"},"signatures":[{"id":55,"name":"new ConfigManager","kind":16384,"kindString":"Constructor signature","flags":{},"comment":{"shortText":"Creates an instance of the ConfigManager"},"parameters":[{"id":56,"name":"container","kind":32768,"kindString":"Parameter","flags":{"isOptional":true},"comment":{"shortText":"The container for the Configs"},"type":{"type":"instrinct","name":"any"}},{"id":57,"name":"loader","kind":32768,"kindString":"Parameter","flags":{"isOptional":true},"comment":{"shortText":"The loader for the Configs\n"},"type":{"type":"instrinct","name":"any"}}],"type":{"type":"reference","name":"ConfigManager","id":50}}]},{"id":51,"name":"configs","kind":1024,"kindString":"Property","flags":{"isExported":true},"comment":{"shortText":"POJO map of the registered configs","tags":[{"tag":"param","text":"\n"}]},"type":{"type":"instrinct","name":"any"}},{"id":52,"name":"container","kind":1024,"kindString":"Property","flags":{"isExported":true},"comment":{"shortText":"The container for the Configs","tags":[{"tag":"param","text":"\n"}]},"type":{"type":"instrinct","name":"any"}},{"id":53,"name":"loader","kind":1024,"kindString":"Property","flags":{"isExported":true},"comment":{"shortText":"The Config loader","tags":[{"tag":"param","text":"\n"}]},"type":{"type":"instrinct","name":"any"}},{"id":69,"name":"addFromContainer","kind":2048,"kindString":"Method","flags":{"isExported":true},"signatures":[{"id":70,"name":"addFromContainer","kind":4096,"kindString":"Call signature","flags":{},"comment":{"shortText":"Add a Config by key from the container","returns":"itself","tags":[{"tag":"chainable","text":"\n"}]},"parameters":[{"id":71,"name":"key","kind":32768,"kindString":"Parameter","flags":{"isOptional":true},"comment":{"text":"The container key"},"type":{"type":"instrinct","name":"any"}},{"id":72,"name":"configObject","kind":32768,"kindString":"Parameter","flags":{"isOptional":true},"comment":{"text":"The configuration object"},"type":{"type":"instrinct","name":"any"}},{"id":73,"name":"alias","kind":32768,"kindString":"Parameter","flags":{"isOptional":true},"comment":{"text":"The aiias to register under if none is set in config.alias"},"type":{"type":"instrinct","name":"any"}},{"id":74,"name":"registerAlias","kind":32768,"kindString":"Parameter","flags":{"isOptional":true},"comment":{"text":"Register with container (true)"},"type":{"type":"instrinct","name":"any"}}],"type":{"type":"instrinct","name":"any"}}]},{"id":64,"name":"addInstance","kind":2048,"kindString":"Method","flags":{"isExported":true},"signatures":[{"id":65,"name":"addInstance","kind":4096,"kindString":"Call signature","flags":{},"comment":{"shortText":"Add a Config from a BaseConfig or Object","returns":"itself","tags":[{"tag":"chainable","text":"\n"}]},"parameters":[{"id":66,"name":"alias","kind":32768,"kindString":"Parameter","flags":{"isOptional":true},"comment":{"text":"The unique alias to register under"},"type":{"type":"instrinct","name":"any"}},{"id":67,"name":"configObject","kind":32768,"kindString":"Parameter","flags":{"isOptional":true},"type":{"type":"instrinct","name":"any"}},{"id":68,"name":"registerAlias","kind":32768,"kindString":"Parameter","flags":{"isOptional":true},"comment":{"text":"Register with container (true)"},"type":{"type":"instrinct","name":"any"}}],"type":{"type":"instrinct","name":"any"}}]},{"id":75,"name":"copy","kind":2048,"kindString":"Method","flags":{"isExported":true},"signatures":[{"id":76,"name":"copy","kind":4096,"kindString":"Call signature","flags":{},"comment":{"shortText":"Deep copy a Config into another","returns":"itself","tags":[{"tag":"chainable","text":"\n"}]},"parameters":[{"id":77,"name":"targetAliasOrKeyOrInstance","kind":32768,"kindString":"Parameter","flags":{"isOptional":true},"comment":{"text":"The target alias, container key or an instance of BaseConfig"},"type":{"type":"instrinct","name":"any"}},{"id":78,"name":"sourceAliasOrKeyOrInstance","kind":32768,"kindString":"Parameter","flags":{"isOptional":true},"comment":{"text":"The source alias, container key or an instance of BaseConfig"},"type":{"type":"instrinct","name":"any"}},{"id":79,"name":"includeDefaults","kind":32768,"kindString":"Parameter","flags":{"isOptional":true},"comment":{"text":"Also copy defaults"},"type":{"type":"instrinct","name":"any"}}],"type":{"type":"instrinct","name":"any"}}]},{"id":80,"name":"extend","kind":2048,"kindString":"Method","flags":{"isExported":true},"signatures":[{"id":81,"name":"extend","kind":4096,"kindString":"Call signature","flags":{},"comment":{"shortText":"Deep extend a Config with another","returns":"itself","tags":[{"tag":"chainable","text":"\n"}]},"parameters":[{"id":82,"name":"targetAliasOrKeyOrInstance","kind":32768,"kindString":"Parameter","flags":{"isOptional":true},"type":{"type":"instrinct","name":"any"}},{"id":83,"name":"sourceAliasOrKeyOrInstance","kind":32768,"kindString":"Parameter","flags":{"isOptional":true},"type":{"type":"instrinct","name":"any"}},{"id":84,"name":"includeDefaults","kind":32768,"kindString":"Parameter","flags":{"isOptional":true},"comment":{"text":"Also merge defaults"},"type":{"type":"instrinct","name":"any"}}],"type":{"type":"instrinct","name":"any"}}]},{"id":61,"name":"get","kind":2048,"kindString":"Method","flags":{"isExported":true},"signatures":[{"id":62,"name":"get","kind":4096,"kindString":"Call signature","flags":{},"comment":{"shortText":"Resolves an alias or container key or instance to Config instance","returns":"that\n"},"parameters":[{"id":63,"name":"aliasOrKeyOrInstance","kind":32768,"kindString":"Parameter","flags":{"isOptional":true},"comment":{"text":"The target alias or container key or a BaseConfig instance"},"type":{"type":"instrinct","name":"any"}}],"type":{"type":"instrinct","name":"any"}}]},{"id":58,"name":"has","kind":2048,"kindString":"Method","flags":{"isExported":true},"signatures":[{"id":59,"name":"has","kind":4096,"kindString":"Call signature","flags":{},"comment":{"shortText":"Has alias registered","returns":"that\n"},"parameters":[{"id":60,"name":"alias","kind":32768,"kindString":"Parameter","flags":{"isOptional":true},"comment":{"text":"The requested alias"},"type":{"type":"instrinct","name":"any"}}],"type":{"type":"instrinct","name":"any"}}]},{"id":89,"name":"load","kind":2048,"kindString":"Method","flags":{"isExported":true},"signatures":[{"id":90,"name":"load","kind":4096,"kindString":"Call signature","flags":{},"comment":{"shortText":"Load a Config from a plugin by moduleId","returns":"\n"},"parameters":[{"id":91,"name":"moduleId","kind":32768,"kindString":"Parameter","flags":{"isOptional":true},"type":{"type":"instrinct","name":"any"}},{"id":92,"name":"configObject","kind":32768,"kindString":"Parameter","flags":{"isOptional":true},"comment":{"text":"The config to merge into load Config"},"type":{"type":"instrinct","name":"any"}},{"id":93,"name":"className","kind":32768,"kindString":"Parameter","flags":{"isOptional":true},"comment":{"text":"The class to load as Config (default = 'Config)')"},"type":{"type":"instrinct","name":"any"}},{"id":94,"name":"registerAlias","kind":32768,"kindString":"Parameter","flags":{"isOptional":true},"type":{"type":"instrinct","name":"any"}}],"type":{"type":"instrinct","name":"any"}}]},{"id":85,"name":"remove","kind":2048,"kindString":"Method","flags":{"isExported":true},"signatures":[{"id":86,"name":"remove","kind":4096,"kindString":"Call signature","flags":{},"comment":{"shortText":"Remove a Config from the ConfigManager","returns":"itself","tags":[{"tag":"chainable","text":"\n"}]},"parameters":[{"id":87,"name":"aliasOrKeyOrInstance","kind":32768,"kindString":"Parameter","flags":{"isOptional":true},"comment":{"text":"The target alias or container key or an instance of BaseConfig"},"type":{"type":"instrinct","name":"any"}},{"id":88,"name":"removeAlias","kind":32768,"kindString":"Parameter","flags":{"isOptional":true},"comment":{"text":"Also remove container alias (true)"},"type":{"type":"instrinct","name":"any"}}],"type":{"type":"instrinct","name":"any"}}]}],"groups":[{"title":"Constructors","kind":512,"children":[54]},{"title":"Properties","kind":1024,"children":[51,52,53]},{"title":"Methods","kind":2048,"children":[69,64,75,80,61,58,89,85]}]},{"id":26,"name":"GlobalConfig","kind":128,"kindString":"Class","flags":{"isExported":true},"comment":{"shortText":"GlobalConfig class"},"children":[{"id":28,"name":"constructor","kind":512,"kindString":"Constructor","flags":{"isExported":true},"signatures":[{"id":29,"name":"new GlobalConfig","kind":16384,"kindString":"Constructor signature","flags":{},"parameters":[{"id":30,"name":"defaults","kind":32768,"kindString":"Parameter","flags":{"isOptional":true},"type":{"type":"instrinct","name":"any"}}],"type":{"type":"reference","name":"GlobalConfig","id":26},"overwrites":{"type":"reference","name":"BaseConfig.__constructor","id":6}}],"overwrites":{"type":"reference","name":"BaseConfig.__constructor","id":6}},{"id":27,"name":"alias","kind":1024,"kindString":"Property","flags":{"isExported":true},"type":{"type":"instrinct","name":"any"},"overwrites":{"type":"reference","name":"BaseConfig.alias","id":5}},{"id":32,"name":"current","kind":1024,"kindString":"Property","flags":{"isExported":true},"comment":{"shortText":"The current values of your config","tags":[{"tag":"param","text":"\n"}]},"type":{"type":"instrinct","name":"any"},"inheritedFrom":{"type":"reference","name":"BaseConfig.current","id":4}},{"id":31,"name":"defaults","kind":1024,"kindString":"Property","flags":{"isExported":true},"comment":{"shortText":"The defaults of your config","tags":[{"tag":"param","text":"\n"}]},"type":{"type":"instrinct","name":"any"},"inheritedFrom":{"type":"reference","name":"BaseConfig.defaults","id":3}},{"id":36,"name":"delete","kind":2048,"kindString":"Method","flags":{"isExported":true},"signatures":[{"id":37,"name":"delete","kind":4096,"kindString":"Call signature","flags":{},"comment":{"shortText":"Deletes a value from the current configuration"},"parameters":[{"id":38,"name":"keys","kind":32768,"kindString":"Parameter","flags":{"isRest":true},"comment":{"text":"(dot-separated) string(s) or array of keys\n"},"type":{"type":"instrinct","isArray":true,"name":"any"}}],"type":{"type":"instrinct","name":"any"},"inheritedFrom":{"type":"reference","name":"BaseConfig.delete","id":12}}],"inheritedFrom":{"type":"reference","name":"BaseConfig.delete","id":12}},{"id":43,"name":"extend","kind":2048,"kindString":"Method","flags":{"isExported":true},"signatures":[{"id":44,"name":"extend","kind":4096,"kindString":"Call signature","flags":{},"comment":{"shortText":"Entends an oject value in the current configuration"},"parameters":[{"id":45,"name":"keys","kind":32768,"kindString":"Parameter","flags":{"isOptional":true},"comment":{"text":"(dot-separated) string(s) or array of keys"},"type":{"type":"instrinct","name":"any"}},{"id":46,"name":"value","kind":32768,"kindString":"Parameter","flags":{"isOptional":true},"comment":{"text":"The value to set\n"},"type":{"type":"instrinct","name":"any"}}],"type":{"type":"instrinct","name":"any"},"inheritedFrom":{"type":"reference","name":"BaseConfig.extend","id":19}}],"inheritedFrom":{"type":"reference","name":"BaseConfig.extend","id":19}},{"id":33,"name":"fetch","kind":2048,"kindString":"Method","flags":{"isExported":true},"signatures":[{"id":34,"name":"fetch","kind":4096,"kindString":"Call signature","flags":{},"comment":{"shortText":"Fetches a value from the current configuration","returns":"that The retrived value\n"},"parameters":[{"id":35,"name":"keys","kind":32768,"kindString":"Parameter","flags":{"isRest":true},"comment":{"text":"(dot-separated) string(s) or array of keys"},"type":{"type":"instrinct","isArray":true,"name":"any"}}],"type":{"type":"instrinct","name":"any"},"inheritedFrom":{"type":"reference","name":"BaseConfig.fetch","id":9}}],"inheritedFrom":{"type":"reference","name":"BaseConfig.fetch","id":9}},{"id":47,"name":"reset","kind":2048,"kindString":"Method","flags":{"isExported":true},"signatures":[{"id":48,"name":"reset","kind":4096,"kindString":"Call signature","flags":{},"comment":{"shortText":"Reset the current configuration back to defaults"},"parameters":[{"id":49,"name":"keys","kind":32768,"kindString":"Parameter","flags":{"isOptional":true},"comment":{"text":"(dot-separated) string(s) or array of keys"},"type":{"type":"instrinct","name":"any"}}],"type":{"type":"instrinct","name":"any"},"inheritedFrom":{"type":"reference","name":"BaseConfig.reset","id":23}}],"inheritedFrom":{"type":"reference","name":"BaseConfig.reset","id":23}},{"id":39,"name":"set","kind":2048,"kindString":"Method","flags":{"isExported":true},"signatures":[{"id":40,"name":"set","kind":4096,"kindString":"Call signature","flags":{},"comment":{"shortText":"Sets a value in the current configuration"},"parameters":[{"id":41,"name":"keys","kind":32768,"kindString":"Parameter","flags":{"isOptional":true},"comment":{"text":"(dot-separated) string(s) or array of keys"},"type":{"type":"instrinct","name":"any"}},{"id":42,"name":"value","kind":32768,"kindString":"Parameter","flags":{"isOptional":true},"comment":{"text":"The value to set\n"},"type":{"type":"instrinct","name":"any"}}],"type":{"type":"instrinct","name":"any"},"inheritedFrom":{"type":"reference","name":"BaseConfig.set","id":15}}],"inheritedFrom":{"type":"reference","name":"BaseConfig.set","id":15}}],"groups":[{"title":"Constructors","kind":512,"children":[28]},{"title":"Properties","kind":1024,"children":[27,32,31]},{"title":"Methods","kind":2048,"children":[36,43,33,47,39]}],"extendedTypes":[{"type":"reference","name":"BaseConfig","id":2}]},{"id":109,"name":"extendIn","kind":64,"kindString":"Function","flags":{"isExported":true},"signatures":[{"id":110,"name":"extendIn","kind":4096,"kindString":"Call signature","flags":{},"comment":{"shortText":"Entends an oject value in data object"},"parameters":[{"id":111,"name":"data","kind":32768,"kindString":"Parameter","flags":{"isOptional":true},"comment":{"text":"The data to extend"},"type":{"type":"instrinct","name":"any"}},{"id":112,"name":"keys","kind":32768,"kindString":"Parameter","flags":{"isOptional":true},"comment":{"text":"(dot-separated) string(s) or array of keys"},"type":{"type":"instrinct","name":"any"}},{"id":113,"name":"value","kind":32768,"kindString":"Parameter","flags":{"isOptional":true},"comment":{"text":"The value to set\n"},"type":{"type":"instrinct","name":"any"}}],"type":{"type":"instrinct","name":"any"}}]},{"id":99,"name":"fetchFrom","kind":64,"kindString":"Function","flags":{"isExported":true},"signatures":[{"id":100,"name":"fetchFrom","kind":4096,"kindString":"Call signature","flags":{},"comment":{"shortText":"Fetches value from (nested) object with a normalized key","returns":"that    The retrieved value from the data\n"},"parameters":[{"id":101,"name":"data","kind":32768,"kindString":"Parameter","flags":{"isOptional":true},"comment":{"text":"The data to fetch data from"},"type":{"type":"instrinct","name":"any"}},{"id":102,"name":"key","kind":32768,"kindString":"Parameter","flags":{"isOptional":true},"type":{"type":"instrinct","name":"any"}},{"id":103,"name":"rest","kind":32768,"kindString":"Parameter","flags":{"isRest":true},"type":{"type":"instrinct","isArray":true,"name":"any"}}],"type":{"type":"instrinct","name":"any"}}]},{"id":95,"name":"normalizeKey","kind":64,"kindString":"Function","flags":{"isExported":true},"signatures":[{"id":96,"name":"normalizeKey","kind":4096,"kindString":"Call signature","flags":{},"comment":{"shortText":"Used to normalize keys of mixed array and dot-separated string to a single array of undotted strings","returns":"that    The key normalized to an array of strings\n"},"parameters":[{"id":97,"name":"key","kind":32768,"kindString":"Parameter","flags":{"isOptional":true},"type":{"type":"instrinct","name":"any"}},{"id":98,"name":"rest","kind":32768,"kindString":"Parameter","flags":{"isRest":true},"type":{"type":"instrinct","isArray":true,"name":"any"}}],"type":{"type":"instrinct","name":"any"}}]},{"id":104,"name":"setIn","kind":64,"kindString":"Function","flags":{"isExported":true},"signatures":[{"id":105,"name":"setIn","kind":4096,"kindString":"Call signature","flags":{},"comment":{"shortText":"Sets a value in data object"},"parameters":[{"id":106,"name":"data","kind":32768,"kindString":"Parameter","flags":{"isOptional":true},"comment":{"text":"The data to set value in"},"type":{"type":"instrinct","name":"any"}},{"id":107,"name":"keys","kind":32768,"kindString":"Parameter","flags":{"isOptional":true},"comment":{"text":"(dot-separated) string(s) or array of keys"},"type":{"type":"instrinct","name":"any"}},{"id":108,"name":"value","kind":32768,"kindString":"Parameter","flags":{"isOptional":true},"comment":{"text":"The value to set\n"},"type":{"type":"instrinct","name":"any"}}],"type":{"type":"instrinct","name":"any"}}]}],"groups":[{"title":"Classes","kind":128,"children":[2,50,26]},{"title":"Functions","kind":64,"children":[109,99,95,104]}]}